bricoleur/__init__.py
bricoleur/stairs.py
bricoleur-0.0.3.dist-info/licenses/LICENSE
bricoleur-0.0.3.dist-info/WHEEL
bricoleur-0.0.3.dist-info/METADATA
bricoleur-0.0.3.dist-info/RECORD
